Metadata-Version: 2.2
Name: lpar_activation_work
Version: 1.0.1
Requires-Dist: gitdb==4.0.12
Requires-Dist: GitPython==3.1.44
Requires-Dist: pytest==8.3.4
Requires-Dist: paramiko==3.5.1
Requires-Dist: requests==2.32.3
Requires-Dist: setuptools==75.8.0
Requires-Dist: zhmccli==1.12.0
Requires-Dist: twine==6.1.0
Requires-Dist: build==1.2.2
Requires-Dist: pipreqs==0.4.13
Dynamic: requires-dist
